{
	"refreshIntervalHrs": 24,
	"dailyPurchaseHrs": 24,
	"expiration": "2023-08-07T04:27:26.542Z",
	"storefronts": [
		{
			"name": "BRDailyStorefront",
			"catalogEntries": [
				{
					"devName": "70ca993533a9bae0e8d8129a02a38f1906b82160",
					"offerId": "70ca993533a9bae0e8d8129a02a38f1906b82160",
					"fulfillmentIds": [],
					"dailyLimit": -1,
					"weeklyLimit": -1,
					"monthlyLimit": -1,
					"categories": [],
					"prices": [
						{
							"currencyType": "MtxCurrency",
							"currencySubType": "CurrencySource",
							"regularPrice": 0,
							"finalPrice": 0,
							"saleExpiration": "2023-08-06T23:59:59.999Z",
							"basePrice": 0
						}
					],
					"meta": {
						"SectionId": "Featured",
						"TileSize": "Small"
					},
					"matchFilter": "",
					"filterWeight": 1,
					"appStoreId": [],
					"requirements": [
						{
							"requirementType": "DenyOnItemOwnership",
							"requiredId": "AthenaLoadingScreen:LSID_110_S8Cumulative04",
							"minQuantity": 1
						}
					],
					"offerType": "StaticPrice",
					"giftInfo": {
						"bIsEnabled": false,
						"forcedGiftBoxTemplateId": "",
						"giftRecordIds": [],
						"purchaseRequirements": []
					},
					"refundable": false,
					"metaInfo": [
						{
							"key": "SectionId",
							"value": "Featured"
						},
						{
							"key": "TileSize",
							"value": "Small"
						}
					],
					"displayAssetPath": "",
					"itemGrants": [
						{
							"templateId": "AthenaLoadingScreen:LSID_110_S8Cumulative04",
							"quantity": 1
						}
					],
					"sortPriority": 1,
					"catalogGroupPriority": 0
				},
				{
					"devName": "96f16e1e1811243a7c149bec564fc133fdf32485",
					"offerId": "96f16e1e1811243a7c149bec564fc133fdf32485",
					"fulfillmentIds": [],
					"dailyLimit": -1,
					"weeklyLimit": -1,
					"monthlyLimit": -1,
					"categories": [],
					"prices": [
						{
							"currencyType": "MtxCurrency",
							"currencySubType": "CurrencySource",
							"regularPrice": 500,
							"finalPrice": 500,
							"saleExpiration": "2023-08-06T23:59:59.999Z",
							"basePrice": 500
						}
					],
					"meta": {
						"SectionId": "Featured",
						"TileSize": "Small"
					},
					"matchFilter": "",
					"filterWeight": 1,
					"appStoreId": [],
					"requirements": [
						{
							"requirementType": "DenyOnItemOwnership",
							"requiredId": "AthenaPickaxe:Pickaxe_ID_091_Hacivat",
							"minQuantity": 1
						}
					],
					"offerType": "StaticPrice",
					"giftInfo": {
						"bIsEnabled": false,
						"forcedGiftBoxTemplateId": "",
						"giftRecordIds": [],
						"purchaseRequirements": []
					},
					"refundable": false,
					"metaInfo": [
						{
							"key": "SectionId",
							"value": "Featured"
						},
						{
							"key": "TileSize",
							"value": "Small"
						}
					],
					"displayAssetPath": "",
					"itemGrants": [
						{
							"templateId": "AthenaPickaxe:Pickaxe_ID_091_Hacivat",
							"quantity": 1
						}
					],
					"sortPriority": 1,
					"catalogGroupPriority": 0
				},
				{
					"devName": "5bad4ba51d66f37ba2b17ea382d91ea7215e2c69",
					"offerId": "5bad4ba51d66f37ba2b17ea382d91ea7215e2c69",
					"fulfillmentIds": [],
					"dailyLimit": -1,
					"weeklyLimit": -1,
					"monthlyLimit": -1,
					"categories": [],
					"prices": [
						{
							"currencyType": "MtxCurrency",
							"currencySubType": "CurrencySource",
							"regularPrice": 500,
							"finalPrice": 500,
							"saleExpiration": "2023-08-06T23:59:59.999Z",
							"basePrice": 500
						}
					],
					"meta": {
						"SectionId": "Featured",
						"TileSize": "Small"
					},
					"matchFilter": "",
					"filterWeight": 1,
					"appStoreId": [],
					"requirements": [
						{
							"requirementType": "DenyOnItemOwnership",
							"requiredId": "AthenaPickaxe:Pickaxe_ID_032_Tactical",
							"minQuantity": 1
						}
					],
					"offerType": "StaticPrice",
					"giftInfo": {
						"bIsEnabled": false,
						"forcedGiftBoxTemplateId": "",
						"giftRecordIds": [],
						"purchaseRequirements": []
					},
					"refundable": false,
					"metaInfo": [
						{
							"key": "SectionId",
							"value": "Featured"
						},
						{
							"key": "TileSize",
							"value": "Small"
						}
					],
					"displayAssetPath": "",
					"itemGrants": [
						{
							"templateId": "AthenaPickaxe:Pickaxe_ID_032_Tactical",
							"quantity": 1
						}
					],
					"sortPriority": 1,
					"catalogGroupPriority": 0
				},
				{
					"devName": "ecfca619cb2fc257caae1388526df19e3dbecdd2",
					"offerId": "ecfca619cb2fc257caae1388526df19e3dbecdd2",
					"fulfillmentIds": [],
					"dailyLimit": -1,
					"weeklyLimit": -1,
					"monthlyLimit": -1,
					"categories": [],
					"prices": [
						{
							"currencyType": "MtxCurrency",
							"currencySubType": "CurrencySource",
							"regularPrice": 0,
							"finalPrice": 0,
							"saleExpiration": "2023-08-06T23:59:59.999Z",
							"basePrice": 0
						}
					],
					"meta": {
						"SectionId": "Featured",
						"TileSize": "Small"
					},
					"matchFilter": "",
					"filterWeight": 1,
					"appStoreId": [],
					"requirements": [
						{
							"requirementType": "DenyOnItemOwnership",
							"requiredId": "AthenaLoadingScreen:LSID_066_S6Cumulative05",
							"minQuantity": 1
						}
					],
					"offerType": "StaticPrice",
					"giftInfo": {
						"bIsEnabled": false,
						"forcedGiftBoxTemplateId": "",
						"giftRecordIds": [],
						"purchaseRequirements": []
					},
					"refundable": false,
					"metaInfo": [
						{
							"key": "SectionId",
							"value": "Featured"
						},
						{
							"key": "TileSize",
							"value": "Small"
						}
					],
					"displayAssetPath": "",
					"itemGrants": [
						{
							"templateId": "AthenaLoadingScreen:LSID_066_S6Cumulative05",
							"quantity": 1
						}
					],
					"sortPriority": 1,
					"catalogGroupPriority": 0
				},
				{
					"devName": "d2f8e7f75e7f0e2057e8174b020a66cdcb159f68",
					"offerId": "d2f8e7f75e7f0e2057e8174b020a66cdcb159f68",
					"fulfillmentIds": [],
					"dailyLimit": -1,
					"weeklyLimit": -1,
					"monthlyLimit": -1,
					"categories": [],
					"prices": [
						{
							"currencyType": "MtxCurrency",
							"currencySubType": "CurrencySource",
							"regularPrice": 1200,
							"finalPrice": 1200,
							"saleExpiration": "2023-08-06T23:59:59.999Z",
							"basePrice": 1200
						}
					],
					"meta": {
						"SectionId": "Featured",
						"TileSize": "Small"
					},
					"matchFilter": "",
					"filterWeight": 1,
					"appStoreId": [],
					"requirements": [
						{
							"requirementType": "DenyOnItemOwnership",
							"requiredId": "AthenaCharacter:CID_025_Athena_Commando_M",
							"minQuantity": 1
						}
					],
					"offerType": "StaticPrice",
					"giftInfo": {
						"bIsEnabled": false,
						"forcedGiftBoxTemplateId": "",
						"giftRecordIds": [],
						"purchaseRequirements": []
					},
					"refundable": false,
					"metaInfo": [
						{
							"key": "SectionId",
							"value": "Featured"
						},
						{
							"key": "TileSize",
							"value": "Small"
						}
					],
					"displayAssetPath": "",
					"itemGrants": [
						{
							"templateId": "AthenaCharacter:CID_025_Athena_Commando_M",
							"quantity": 1
						}
					],
					"sortPriority": 1,
					"catalogGroupPriority": 0
				},
				{
					"devName": "aae6ab4e7f814b65465661d4ba6b59526451cbf8",
					"offerId": "aae6ab4e7f814b65465661d4ba6b59526451cbf8",
					"fulfillmentIds": [],
					"dailyLimit": -1,
					"weeklyLimit": -1,
					"monthlyLimit": -1,
					"categories": [],
					"prices": [
						{
							"currencyType": "MtxCurrency",
							"currencySubType": "CurrencySource",
							"regularPrice": 200,
							"finalPrice": 200,
							"saleExpiration": "2023-08-06T23:59:59.999Z",
							"basePrice": 200
						}
					],
					"meta": {
						"SectionId": "Featured",
						"TileSize": "Small"
					},
					"matchFilter": "",
					"filterWeight": 1,
					"appStoreId": [],
					"requirements": [
						{
							"requirementType": "DenyOnItemOwnership",
							"requiredId": "AthenaDance:EID_MartialArts",
							"minQuantity": 1
						}
					],
					"offerType": "StaticPrice",
					"giftInfo": {
						"bIsEnabled": false,
						"forcedGiftBoxTemplateId": "",
						"giftRecordIds": [],
						"purchaseRequirements": []
					},
					"refundable": false,
					"metaInfo": [
						{
							"key": "SectionId",
							"value": "Featured"
						},
						{
							"key": "TileSize",
							"value": "Small"
						}
					],
					"displayAssetPath": "",
					"itemGrants": [
						{
							"templateId": "AthenaDance:EID_MartialArts",
							"quantity": 1
						}
					],
					"sortPriority": 1,
					"catalogGroupPriority": 0
				}
			]
		},
		{
			"name": "BRWeeklyStorefront",
			"catalogEntries": [
				{
					"devName": "5dfe1e51c5cc5bb4ed3a95336c1104ba27ad0740",
					"offerId": "5dfe1e51c5cc5bb4ed3a95336c1104ba27ad0740",
					"fulfillmentIds": [],
					"dailyLimit": -1,
					"weeklyLimit": -1,
					"monthlyLimit": -1,
					"categories": [],
					"prices": [
						{
							"currencyType": "MtxCurrency",
							"currencySubType": "CurrencySource",
							"regularPrice": 2000,
							"finalPrice": 2000,
							"saleExpiration": "2023-08-06T23:59:59.999Z",
							"basePrice": 2000
						}
					],
					"meta": {
						"SectionId": "Featured",
						"TileSize": "Small"
					},
					"matchFilter": "",
					"filterWeight": -1,
					"appStoreId": [],
					"requirements": [
						{
							"requirementType": "DenyOnItemOwnership",
							"requiredId": "AthenaCharacter:CID_115_Athena_Commando_M_CarbideBlue",
							"minQuantity": 1
						}
					],
					"offerType": "StaticPrice",
					"giftInfo": {
						"bIsEnabled": false,
						"forcedGiftBoxTemplateId": "",
						"giftRecordIds": [],
						"purchaseRequirements": []
					},
					"refundable": false,
					"metaInfo": [
						{
							"key": "SectionId",
							"value": "Featured"
						},
						{
							"key": "TileSize",
							"value": "Small"
						}
					],
					"displayAssetPath": "",
					"itemGrants": [
						{
							"templateId": "AthenaCharacter:CID_115_Athena_Commando_M_CarbideBlue",
							"quantity": 1
						}
					],
					"sortPriority": -1,
					"catalogGroupPriority": 0
				},
				{
					"devName": "2db0b0d8463cbf85294aa6bbdeb7ecc9e4b4e024",
					"offerId": "2db0b0d8463cbf85294aa6bbdeb7ecc9e4b4e024",
					"fulfillmentIds": [],
					"dailyLimit": -1,
					"weeklyLimit": -1,
					"monthlyLimit": -1,
					"categories": [],
					"prices": [
						{
							"currencyType": "MtxCurrency",
							"currencySubType": "CurrencySource",
							"regularPrice": 2000,
							"finalPrice": 2000,
							"saleExpiration": "2023-08-06T23:59:59.999Z",
							"basePrice": 2000
						}
					],
					"meta": {
						"SectionId": "Featured",
						"TileSize": "Small"
					},
					"matchFilter": "",
					"filterWeight": -1,
					"appStoreId": [],
					"requirements": [
						{
							"requirementType": "DenyOnItemOwnership",
							"requiredId": "AthenaCharacter:CID_142_Athena_Commando_M_WWIIPilot",
							"minQuantity": 1
						}
					],
					"offerType": "StaticPrice",
					"giftInfo": {
						"bIsEnabled": false,
						"forcedGiftBoxTemplateId": "",
						"giftRecordIds": [],
						"purchaseRequirements": []
					},
					"refundable": false,
					"metaInfo": [
						{
							"key": "SectionId",
							"value": "Featured"
						},
						{
							"key": "TileSize",
							"value": "Small"
						}
					],
					"displayAssetPath": "",
					"itemGrants": [
						{
							"templateId": "AthenaCharacter:CID_142_Athena_Commando_M_WWIIPilot",
							"quantity": 1
						}
					],
					"sortPriority": -1,
					"catalogGroupPriority": 0
				}
			]
		},
		{
			"name": "BRSeasonStorefront",
			"catalogEntries": []
		}
	]
}