{
	"refreshIntervalHrs": 24,
	"dailyPurchaseHrs": 24,
	"expiration": "2023-08-14T23:59:59.999Z",
	"storefronts": [
		{
			"name": "BRDailyStorefront",
			"catalogEntries": [
				{
					"devName": "a38d0fe2ee8729c15a30ff93e9a1bd0bdd6a614c",
					"offerId": "a38d0fe2ee8729c15a30ff93e9a1bd0bdd6a614c",
					"fulfillmentIds": [],
					"dailyLimit": -1,
					"weeklyLimit": -1,
					"monthlyLimit": -1,
					"categories": [],
					"prices": [
						{
							"currencyType": "MtxCurrency",
							"currencySubType": "CurrencySource",
							"regularPrice": 500,
							"finalPrice": 500,
							"saleExpiration": "2023-08-14T23:59:59.999Z",
							"basePrice": 500
						}
					],
					"meta": {
						"SectionId": "Featured",
						"TileSize": "Small"
					},
					"matchFilter": "",
					"filterWeight": 1,
					"appStoreId": [],
					"requirements": [
						{
							"requirementType": "DenyOnItemOwnership",
							"requiredId": "AthenaCharacter:CID_005_Athena_Commando_M_Default",
							"minQuantity": 1
						}
					],
					"offerType": "StaticPrice",
					"giftInfo": {
						"bIsEnabled": false,
						"forcedGiftBoxTemplateId": "",
						"giftRecordIds": [],
						"purchaseRequirements": []
					},
					"refundable": false,
					"metaInfo": [
						{
							"key": "SectionId",
							"value": "Featured"
						},
						{
							"key": "TileSize",
							"value": "Small"
						}
					],
					"displayAssetPath": "",
					"itemGrants": [
						{
							"templateId": "AthenaCharacter:CID_005_Athena_Commando_M_Default",
							"quantity": 1
						}
					],
					"sortPriority": 1,
					"catalogGroupPriority": 0
				},
				{
					"devName": "7acdf6b6452239ea07065506d911e61c245a530a",
					"offerId": "7acdf6b6452239ea07065506d911e61c245a530a",
					"fulfillmentIds": [],
					"dailyLimit": -1,
					"weeklyLimit": -1,
					"monthlyLimit": -1,
					"categories": [],
					"prices": [
						{
							"currencyType": "MtxCurrency",
							"currencySubType": "CurrencySource",
							"regularPrice": 500,
							"finalPrice": 500,
							"saleExpiration": "2023-08-14T23:59:59.999Z",
							"basePrice": 500
						}
					],
					"meta": {
						"SectionId": "Featured",
						"TileSize": "Small"
					},
					"matchFilter": "",
					"filterWeight": 1,
					"appStoreId": [],
					"requirements": [
						{
							"requirementType": "DenyOnItemOwnership",
							"requiredId": "AthenaGlider:Glider_ID_113_Barbarian",
							"minQuantity": 1
						}
					],
					"offerType": "StaticPrice",
					"giftInfo": {
						"bIsEnabled": false,
						"forcedGiftBoxTemplateId": "",
						"giftRecordIds": [],
						"purchaseRequirements": []
					},
					"refundable": false,
					"metaInfo": [
						{
							"key": "SectionId",
							"value": "Featured"
						},
						{
							"key": "TileSize",
							"value": "Small"
						}
					],
					"displayAssetPath": "",
					"itemGrants": [
						{
							"templateId": "AthenaGlider:Glider_ID_113_Barbarian",
							"quantity": 1
						}
					],
					"sortPriority": 1,
					"catalogGroupPriority": 0
				},
				{
					"devName": "b994ca28f66c2d916e625cc0da6955d5d59fc436",
					"offerId": "b994ca28f66c2d916e625cc0da6955d5d59fc436",
					"fulfillmentIds": [],
					"dailyLimit": -1,
					"weeklyLimit": -1,
					"monthlyLimit": -1,
					"categories": [],
					"prices": [
						{
							"currencyType": "MtxCurrency",
							"currencySubType": "CurrencySource",
							"regularPrice": 500,
							"finalPrice": 500,
							"saleExpiration": "2023-08-14T23:59:59.999Z",
							"basePrice": 500
						}
					],
					"meta": {
						"SectionId": "Featured",
						"TileSize": "Small"
					},
					"matchFilter": "",
					"filterWeight": 1,
					"appStoreId": [],
					"requirements": [
						{
							"requirementType": "DenyOnItemOwnership",
							"requiredId": "AthenaDance:EID_KEagle",
							"minQuantity": 1
						}
					],
					"offerType": "StaticPrice",
					"giftInfo": {
						"bIsEnabled": false,
						"forcedGiftBoxTemplateId": "",
						"giftRecordIds": [],
						"purchaseRequirements": []
					},
					"refundable": false,
					"metaInfo": [
						{
							"key": "SectionId",
							"value": "Featured"
						},
						{
							"key": "TileSize",
							"value": "Small"
						}
					],
					"displayAssetPath": "",
					"itemGrants": [
						{
							"templateId": "AthenaDance:EID_KEagle",
							"quantity": 1
						}
					],
					"sortPriority": 1,
					"catalogGroupPriority": 0
				},
				{
					"devName": "c33a715d4fab8e2eb875986a5e8c0074870273d2",
					"offerId": "c33a715d4fab8e2eb875986a5e8c0074870273d2",
					"fulfillmentIds": [],
					"dailyLimit": -1,
					"weeklyLimit": -1,
					"monthlyLimit": -1,
					"categories": [],
					"prices": [
						{
							"currencyType": "MtxCurrency",
							"currencySubType": "CurrencySource",
							"regularPrice": 500,
							"finalPrice": 500,
							"saleExpiration": "2023-08-14T23:59:59.999Z",
							"basePrice": 500
						}
					],
					"meta": {
						"SectionId": "Featured",
						"TileSize": "Small"
					},
					"matchFilter": "",
					"filterWeight": 1,
					"appStoreId": [],
					"requirements": [
						{
							"requirementType": "DenyOnItemOwnership",
							"requiredId": "AthenaDance:EID_FireworksSpin",
							"minQuantity": 1
						}
					],
					"offerType": "StaticPrice",
					"giftInfo": {
						"bIsEnabled": false,
						"forcedGiftBoxTemplateId": "",
						"giftRecordIds": [],
						"purchaseRequirements": []
					},
					"refundable": false,
					"metaInfo": [
						{
							"key": "SectionId",
							"value": "Featured"
						},
						{
							"key": "TileSize",
							"value": "Small"
						}
					],
					"displayAssetPath": "",
					"itemGrants": [
						{
							"templateId": "AthenaDance:EID_FireworksSpin",
							"quantity": 1
						}
					],
					"sortPriority": 1,
					"catalogGroupPriority": 0
				},
				{
					"devName": "dc77dfcef95f08d186ee66fa0b86b28dfe9f2b25",
					"offerId": "dc77dfcef95f08d186ee66fa0b86b28dfe9f2b25",
					"fulfillmentIds": [],
					"dailyLimit": -1,
					"weeklyLimit": -1,
					"monthlyLimit": -1,
					"categories": [],
					"prices": [
						{
							"currencyType": "MtxCurrency",
							"currencySubType": "CurrencySource",
							"regularPrice": 0,
							"finalPrice": 0,
							"saleExpiration": "2023-08-14T23:59:59.999Z",
							"basePrice": 0
						}
					],
					"meta": {
						"SectionId": "Featured",
						"TileSize": "Small"
					},
					"matchFilter": "",
					"filterWeight": 1,
					"appStoreId": [],
					"requirements": [
						{
							"requirementType": "DenyOnItemOwnership",
							"requiredId": "AthenaLoadingScreen:LSID_100_StPattyDay",
							"minQuantity": 1
						}
					],
					"offerType": "StaticPrice",
					"giftInfo": {
						"bIsEnabled": false,
						"forcedGiftBoxTemplateId": "",
						"giftRecordIds": [],
						"purchaseRequirements": []
					},
					"refundable": false,
					"metaInfo": [
						{
							"key": "SectionId",
							"value": "Featured"
						},
						{
							"key": "TileSize",
							"value": "Small"
						}
					],
					"displayAssetPath": "",
					"itemGrants": [
						{
							"templateId": "AthenaLoadingScreen:LSID_100_StPattyDay",
							"quantity": 1
						}
					],
					"sortPriority": 1,
					"catalogGroupPriority": 0
				},
				{
					"devName": "e5b34b94b1fae071d9d9115e96a16f459d5b6c2f",
					"offerId": "e5b34b94b1fae071d9d9115e96a16f459d5b6c2f",
					"fulfillmentIds": [],
					"dailyLimit": -1,
					"weeklyLimit": -1,
					"monthlyLimit": -1,
					"categories": [],
					"prices": [
						{
							"currencyType": "MtxCurrency",
							"currencySubType": "CurrencySource",
							"regularPrice": 1500,
							"finalPrice": 1500,
							"saleExpiration": "2023-08-14T23:59:59.999Z",
							"basePrice": 1500
						}
					],
					"meta": {
						"SectionId": "Featured",
						"TileSize": "Small"
					},
					"matchFilter": "",
					"filterWeight": 1,
					"appStoreId": [],
					"requirements": [
						{
							"requirementType": "DenyOnItemOwnership",
							"requiredId": "AthenaCharacter:CID_159_Athena_Commando_M_GumshoeDark",
							"minQuantity": 1
						}
					],
					"offerType": "StaticPrice",
					"giftInfo": {
						"bIsEnabled": false,
						"forcedGiftBoxTemplateId": "",
						"giftRecordIds": [],
						"purchaseRequirements": []
					},
					"refundable": false,
					"metaInfo": [
						{
							"key": "SectionId",
							"value": "Featured"
						},
						{
							"key": "TileSize",
							"value": "Small"
						}
					],
					"displayAssetPath": "",
					"itemGrants": [
						{
							"templateId": "AthenaCharacter:CID_159_Athena_Commando_M_GumshoeDark",
							"quantity": 1
						}
					],
					"sortPriority": 1,
					"catalogGroupPriority": 0
				}
			]
		},
		{
			"name": "BRWeeklyStorefront",
			"catalogEntries": [
				{
					"devName": "5f88d7b4a1b13716cf59f9bbfc0195f94301621d",
					"offerId": "5f88d7b4a1b13716cf59f9bbfc0195f94301621d",
					"fulfillmentIds": [],
					"dailyLimit": -1,
					"weeklyLimit": -1,
					"monthlyLimit": -1,
					"categories": [],
					"prices": [
						{
							"currencyType": "MtxCurrency",
							"currencySubType": "CurrencySource",
							"regularPrice": 2000,
							"finalPrice": 2000,
							"saleExpiration": "2023-08-14T23:59:59.999Z",
							"basePrice": 2000
						}
					],
					"meta": {
						"SectionId": "Featured",
						"TileSize": "Small"
					},
					"matchFilter": "",
					"filterWeight": -1,
					"appStoreId": [],
					"requirements": [
						{
							"requirementType": "DenyOnItemOwnership",
							"requiredId": "AthenaCharacter:CID_105_Athena_Commando_F_SpaceBlack",
							"minQuantity": 1
						}
					],
					"offerType": "StaticPrice",
					"giftInfo": {
						"bIsEnabled": false,
						"forcedGiftBoxTemplateId": "",
						"giftRecordIds": [],
						"purchaseRequirements": []
					},
					"refundable": false,
					"metaInfo": [
						{
							"key": "SectionId",
							"value": "Featured"
						},
						{
							"key": "TileSize",
							"value": "Small"
						}
					],
					"displayAssetPath": "",
					"itemGrants": [
						{
							"templateId": "AthenaCharacter:CID_105_Athena_Commando_F_SpaceBlack",
							"quantity": 1
						}
					],
					"sortPriority": -1,
					"catalogGroupPriority": 0
				},
				{
					"devName": "0987d432ffa1a1981b995d8f9ef8d2860803a13e",
					"offerId": "0987d432ffa1a1981b995d8f9ef8d2860803a13e",
					"fulfillmentIds": [],
					"dailyLimit": -1,
					"weeklyLimit": -1,
					"monthlyLimit": -1,
					"categories": [],
					"prices": [
						{
							"currencyType": "MtxCurrency",
							"currencySubType": "CurrencySource",
							"regularPrice": 2000,
							"finalPrice": 2000,
							"saleExpiration": "2023-08-14T23:59:59.999Z",
							"basePrice": 2000
						}
					],
					"meta": {
						"SectionId": "Featured",
						"TileSize": "Small"
					},
					"matchFilter": "",
					"filterWeight": -1,
					"appStoreId": [],
					"requirements": [
						{
							"requirementType": "DenyOnItemOwnership",
							"requiredId": "AthenaCharacter:CID_206_Athena_Commando_M_Bling",
							"minQuantity": 1
						}
					],
					"offerType": "StaticPrice",
					"giftInfo": {
						"bIsEnabled": false,
						"forcedGiftBoxTemplateId": "",
						"giftRecordIds": [],
						"purchaseRequirements": []
					},
					"refundable": false,
					"metaInfo": [
						{
							"key": "SectionId",
							"value": "Featured"
						},
						{
							"key": "TileSize",
							"value": "Small"
						}
					],
					"displayAssetPath": "",
					"itemGrants": [
						{
							"templateId": "AthenaCharacter:CID_206_Athena_Commando_M_Bling",
							"quantity": 1
						}
					],
					"sortPriority": -1,
					"catalogGroupPriority": 0
				}
			]
		},
		{
			"name": "BRSeasonStorefront",
			"catalogEntries": []
		}
	]
}